MANIFEST.in
README.rst
setup.cfg
setup.py
dtoolutils/__init__.py
dtoolutils/overlays.py
dtoolutils.egg-info/PKG-INFO
dtoolutils.egg-info/SOURCES.txt
dtoolutils.egg-info/dependency_links.txt
dtoolutils.egg-info/requires.txt
dtoolutils.egg-info/top_level.txt