Metadata-Version: 1.1
Name: dtoolutils
Version: 0.1.0
Summary: Utilities for working with dtoolcore
Home-page: https://github.com/JIC-CSB/dtoolutils
Author: Tjelvar Olsson
Author-email: tjelvar.olsson@jic.ac.uk
License: MIT
Download-URL: https://github.com/JIC-CSB/dtoolutils/tarball/0.1.0
Platform: UNKNOWN
